GIMPy_Widget_UI/AnalogGauge.py
GIMPy_Widget_UI/Btn_S1.py
GIMPy_Widget_UI/Btn_S2.py
GIMPy_Widget_UI/CheckBox_S1.py
GIMPy_Widget_UI/CheckBox_S2.py
GIMPy_Widget_UI/ON_OFF.py
GIMPy_Widget_UI/Radio_S1.py
GIMPy_Widget_UI/Radio_S2.py
GIMPy_Widget_UI/Shaped_Window.py
GIMPy_Widget_UI/Slider_S1.py
GIMPy_Widget_UI/Toggle_S1.py
GIMPy_Widget_UI/__init__.py
GIMPy_Widget_UI/knob_S1.py
GIMPy_Widget_UI/map_gimpy.py
GIMPy_Widget_UI_010/AnalogGauge.py
GIMPy_Widget_UI_010/Btn_S1.py
GIMPy_Widget_UI_010/Btn_S2.py
GIMPy_Widget_UI_010/CheckBox_S1.py
GIMPy_Widget_UI_010/CheckBox_S2.py
GIMPy_Widget_UI_010/ON_OFF.py
GIMPy_Widget_UI_010/Radio_S1.py
GIMPy_Widget_UI_010/Radio_S2.py
GIMPy_Widget_UI_010/Slider_S1.py
GIMPy_Widget_UI_010/__init__.py
GIMPy_Widget_UI_010/knob_S1.py
GIMPy_Widget_UI_010/map_gimpy.py
GIMPy_Widget_UI-0.1.1.dist-info/LICENSE.txt
GIMPy_Widget_UI-0.1.1.dist-info/METADATA
GIMPy_Widget_UI-0.1.1.dist-info/WHEEL
GIMPy_Widget_UI-0.1.1.dist-info/entry_points.txt
GIMPy_Widget_UI-0.1.1.dist-info/top_level.txt
GIMPy_Widget_UI-0.1.1.dist-info/RECORD
