Metadata-Version: 2.1
Name: GIMPy_Widget_UI
Version: 0.1.1
Summary: Python classes supporting use of GUI created in GIMP
Author: Manish Kathuria
Author-email: gimpywidgetui@gmail.com
License-File: LICENSE.txt
Requires-Dist: asttokens
Requires-Dist: pillow
Requires-Dist: opencv-python
Requires-Dist: numpy
